rds_tunnel/__init__.py
rds_tunnel/cli.py
rds_tunnel/config_manager.py
rds_tunnel/daemon.py
rds_tunnel/garbage_collection.py
rds_tunnel/tunnel_manager.py
rds_tunnel-2.0.0.dist-info/METADATA
rds_tunnel-2.0.0.dist-info/WHEEL
rds_tunnel-2.0.0.dist-info/entry_points.txt
rds_tunnel-2.0.0.dist-info/top_level.txt
rds_tunnel-2.0.0.dist-info/RECORD
