Metadata-Version: 2.4
Name: rds-tunnel
Version: 2.0.0
Summary: Simple SSH Tunnel tool for connecting to RDS. Supports MySQL and PostgreSQL.
Author-email: Sebastian Bekx <sbekx@psb.pw>
Requires-Python: >=3.9
Requires-Dist: boto3>=1.40.8
Requires-Dist: mysql-connector-python>=9.4.0
Requires-Dist: paramiko==2.11.0
Requires-Dist: sshtunnel>=0.4.0
